few_shots/__init__.py
few_shots/async_client.py
few_shots/client.py
few_shots/types.py
few_shots/embed/__init__.py
few_shots/embed/base.py
few_shots/embed/fastembed.py
few_shots/embed/openai.py
few_shots/embed/transformers.py
few_shots/store/__init__.py
few_shots/store/base.py
few_shots/store/chroma.py
few_shots/store/memory.py
few_shots/store/milvus.py
few_shots/store/pg.py
few_shots/store/qdrant.py
few_shots/store/turbopuffer.py
few_shots/store/weaviate.py
few_shots/utils/asyncio.py
few_shots/utils/datetime.py
few_shots/utils/format.py
few_shots-0.4.0.dist-info/METADATA
few_shots-0.4.0.dist-info/WHEEL
few_shots-0.4.0.dist-info/RECORD
