Metadata-Version: 2.3
Name: few-shots
Version: 0.4.0
Summary: Take your best shot
Author-email: cyrus <cyrus@zenbase.ai>, behradkhorram <behrad@zenbase.ai>
Requires-Python: >=3.8
Requires-Dist: asyncer>=0.0.8
Requires-Dist: sorcery>=0.2.2
Requires-Dist: ujson>=5.10.0
